stringfish/__init__.py
stringfish-1.2.dist-info/METADATA
stringfish-1.2.dist-info/RECORD
stringfish-1.2.dist-info/WHEEL
stringfish-1.2.dist-info/top_level.txt
