Metadata-Version: 2.1
Name: stringfish
Version: 1.2
Summary: Ultra-thin wrapper around subprocess for simple default use with string commands
Home-page: http://github.com/gregorpatof/stringfish
Author: gregorpatof
Author-email: gr3gorpatof@gmail.com
License: UNKNOWN
Platform: UNKNOWN
Classifier: Programming Language :: Python :: 3
Classifier: License :: OSI Approved :: MIT License
Classifier: Operating System :: OS Independent
